Metadata-Version: 2.0
Name: hello-world-1989
Version: 0.0.2
Summary: A module to reply hello to a user
Home-page: https://github.com/Ollymid/hello_world_1989
Author: Olly Middleton
Author-email: ollymiddleton2@gmail.com
License: MIT
Platform: UNKNOWN
